chatmates/__init__.py
chatmates/agent.py
chatmates/app/__init__.py
chatmates/app/doc_ask.py
chatmates/common.py
chatmates/embed.py
chatmates/indices.py
chatmates/mind.py
chatmates-0.0.1.dist-info/LICENSE
chatmates-0.0.1.dist-info/METADATA
chatmates-0.0.1.dist-info/WHEEL
chatmates-0.0.1.dist-info/RECORD
