Metadata-Version: 2.1
Name: chatmates
Version: 0.0.1
Summary: Chatty Agents
Home-page: https://github.com/ekshaks/chatmates
License: Apache License, Version 2.0
Keywords: LLM,QA,IR
Author: Nishant Sinha
Author-email: nishant@offnote.co
Requires-Python: >=3.10
Classifier: License :: Other/Proprietary License
Classifier: Programming Language :: Python :: 3
Classifier: Programming Language :: Python :: 3.10
Classifier: Programming Language :: Python :: 3.11
Project-URL: Repository, https://github.com/ekshaks/chatmates
